[
    {
        "key": "dbln",
        "value": "%7B%2261580403217117%22%3A%222RY2uOmW%22%2C%2261583806204532%22%3A%22Qf6HyOYZ%22%7D",
        "domain": "facebook.com",
        "path": "/login/device-based/",
        "hostOnly": false,
        "creation": "2025-11-29T18:24:42.445Z",
        "lastAccessed": "2025-11-29T18:24:42.445Z"
    },
    {
        "key": "datr",
        "value": "mLIkaWO-mp6aqgFimbDn8kHZ",
        "domain": "facebook.com",
        "path": "/",
        "hostOnly": false,
        "creation": "2025-11-29T18:24:42.445Z",
        "lastAccessed": "2025-11-29T18:24:42.445Z"
    },
    {
        "key": "sb",
        "value": "mLIkafIYjWYVakNVWws-9Inc",
        "domain": "facebook.com",
        "path": "/",
        "hostOnly": false,
        "creation": "2025-11-29T18:24:42.445Z",
        "lastAccessed": "2025-11-29T18:24:42.445Z"
    },
    {
        "key": "ps_l",
        "value": "1",
        "domain": "facebook.com",
        "path": "/",
        "hostOnly": false,
        "creation": "2025-11-29T18:24:42.445Z",
        "lastAccessed": "2025-11-29T18:24:42.445Z"
    },
    {
        "key": "ps_n",
        "value": "1",
        "domain": "facebook.com",
        "path": "/",
        "hostOnly": false,
        "creation": "2025-11-29T18:24:42.445Z",
        "lastAccessed": "2025-11-29T18:24:42.445Z"
    },
    {
        "key": "locale",
        "value": "en_GB",
        "domain": "facebook.com",
        "path": "/",
        "hostOnly": false,
        "creation": "2025-11-29T18:24:42.445Z",
        "lastAccessed": "2025-11-29T18:24:42.445Z"
    },
    {
        "key": "vpd",
        "value": "v1%3B838x437x2.1042819023132324",
        "domain": "facebook.com",
        "path": "/",
        "hostOnly": false,
        "creation": "2025-11-29T18:24:42.445Z",
        "lastAccessed": "2025-11-29T18:24:42.445Z"
    },
    {
        "key": "dpr",
        "value": "2.1042819023132324",
        "domain": "facebook.com",
        "path": "/",
        "hostOnly": false,
        "creation": "2025-11-29T18:24:42.445Z",
        "lastAccessed": "2025-11-29T18:24:42.445Z"
    },
    {
        "key": "m_pixel_ratio",
        "value": "2.1042819023132324",
        "domain": "facebook.com",
        "path": "/",
        "hostOnly": false,
        "creation": "2025-11-29T18:24:42.445Z",
        "lastAccessed": "2025-11-29T18:24:42.445Z"
    },
    {
        "key": "wd",
        "value": "437x972",
        "domain": "facebook.com",
        "path": "/",
        "hostOnly": false,
        "creation": "2025-11-29T18:24:42.446Z",
        "lastAccessed": "2025-11-29T18:24:42.446Z"
    },
    {
        "key": "c_user",
        "value": "61583806204532",
        "domain": "facebook.com",
        "path": "/",
        "hostOnly": false,
        "creation": "2025-11-29T18:24:42.446Z",
        "lastAccessed": "2025-11-29T18:24:42.446Z"
    },
    {
        "key": "xs",
        "value": "42%3AXGn9NX2yHvW3AA%3A2%3A1764439986%3A-1%3A-1",
        "domain": "facebook.com",
        "path": "/",
        "hostOnly": false,
        "creation": "2025-11-29T18:24:42.446Z",
        "lastAccessed": "2025-11-29T18:24:42.446Z"
    },
    {
        "key": "fr",
        "value": "0ah06d5HRJJbkA38A.AWesjI00uoisRyyWVY7ZSkyhfO3y-kPlUaWgIBjoThu-kl55Rho.BpJLKY..AAA.0.0.BpKze5.AWdNRpgiq3iHDV0pOg3BGTT5VdA",
        "domain": "facebook.com",
        "path": "/",
        "hostOnly": false,
        "creation": "2025-11-29T18:24:42.446Z",
        "lastAccessed": "2025-11-29T18:24:42.446Z"
    },
    {
        "key": "pas",
        "value": "61580403217117%3AV1tKxR5Wa4%2C61583806204532%3APsiDxPqEz5",
        "domain": "facebook.com",
        "path": "/",
        "hostOnly": false,
        "creation": "2025-11-29T18:24:42.446Z",
        "lastAccessed": "2025-11-29T18:24:42.446Z"
    },
    {
        "key": "wl_cbv",
        "value": "v2%3Bclient_version%3A3000%3Btimestamp%3A1764439993",
        "domain": "facebook.com",
        "path": "/",
        "hostOnly": false,
        "creation": "2025-11-29T18:24:42.446Z",
        "lastAccessed": "2025-11-29T18:24:42.446Z"
    },
    {
        "key": "fbl_st",
        "value": "100618444%3BT%3A29407344",
        "domain": "facebook.com",
        "path": "/",
        "hostOnly": false,
        "creation": "2025-11-29T18:24:42.446Z",
        "lastAccessed": "2025-11-29T18:24:42.446Z"
    }
        ]
